funcrpn/__init__.py
funcrpn/__main__.py
funcrpn/operators.py
funcrpn/stack.py
funcrpn/tests/test_operators.py
funcrpn/tests/test_stack.py
funcrpn/tests/test_stuff.py
funcrpn-1.0.0.dist-info/LICENSE
funcrpn-1.0.0.dist-info/WHEEL
funcrpn-1.0.0.dist-info/METADATA
funcrpn-1.0.0.dist-info/RECORD
